pysqlformatter/__init__.py
pysqlformatter/__main__.py
pysqlformatter/src/__init__.py
pysqlformatter/src/api.py
pysqlformatter/src/formatter.py
pysqlformatter/src/token.py
pysqlformatter/src/tokenizer.py
pysqlformatter/tests/__init__.py
pysqlformatter/tests/pysqlformatter_test.py
pysqlformatter-0.0.7.dist-info/LICENSE
pysqlformatter-0.0.7.dist-info/METADATA
pysqlformatter-0.0.7.dist-info/WHEEL
pysqlformatter-0.0.7.dist-info/entry_points.txt
pysqlformatter-0.0.7.dist-info/top_level.txt
pysqlformatter-0.0.7.dist-info/RECORD
