Metadata-Version: 2.1
Name: pysqlformatter
Version: 0.0.7
Summary: A formatter for Python code and SparkSQL queries.
Home-page: https://github.com/largecats/pyspark-sql-formatter
Author: largecats
Author-email: linfanxiaolinda@outlook.com
License: UNKNOWN
Platform: UNKNOWN
Classifier: Programming Language :: Python
Classifier: Programming Language :: Python :: 2
Classifier: Programming Language :: Python :: 2.7
Classifier: Programming Language :: Python :: 3
Classifier: Programming Language :: Python :: 3.6
Classifier: License :: OSI Approved :: MIT License
Classifier: Operating System :: OS Independent
License-File: LICENSE
Requires-Dist: yapf
Requires-Dist: sparksqlformatter (>=0.1.12)
Requires-Dist: configparser
